{"device_name": "NVIDIA RTX A4000", "cuda_version": 12040, "compute_capability": "86", "iterations": 32, "compiler_options": ["-I/home/fjwillem/Code/kernel_tuner_paper/kernels/gemm_cltune_cuda/", "--std=c++11", "--gpu-architecture=compute_80"], "device_properties": "name : NVIDIA RTX A4000, uuid :,     bytes : 9dde37ed7c5caa1402c10e6e21f41829, luid : 0000000000000000, luidDeviceNodeMask : 0, totalGlobalMem : 16888365056, sharedMemPerBlock : 49152, regsPerBlock : 65536, warpSize : 32, memPitch : 2147483647, maxThreadsPerBlock : 1024, maxThreadsDim : [1024, 1024, 64], maxGridSize : [2147483647, 65535, 65535], clockRate : 1560000, totalConstMem : 65536, major : 8, minor : 6, textureAlignment : 512, texturePitchAlignment : 32, deviceOverlap : 1, multiProcessorCount : 48, kernelExecTimeoutEnabled : 0, integrated : 0, canMapHostMemory : 1, computeMode : 0, maxTexture1D : 131072, maxTexture1DMipmap : 32768, maxTexture1DLinear : 268435456, maxTexture2D : [131072, 65536], maxTexture2DMipmap : [32768, 32768], maxTexture2DLinear : [131072, 65000, 2097120], maxTexture2DGather : [32768, 32768], maxTexture3D : [16384, 16384, 16384], maxTexture3DAlt : [8192, 8192, 32768], maxTextureCubemap : 32768, maxTexture1DLayered : [32768, 2048], maxTexture2DLayered : [32768, 32768, 2048], maxTextureCubemapLayered : [32768, 2046], maxSurface1D : 32768, maxSurface2D : [131072, 65536], maxSurface3D : [16384, 16384, 16384], maxSurface1DLayered : [32768, 2048], maxSurface2DLayered : [32768, 32768, 2048], maxSurfaceCubemap : 32768, maxSurfaceCubemapLayered : [32768, 2046], surfaceAlignment : 512, concurrentKernels : 1, ECCEnabled : 0, pciBusID : 65, pciDeviceID : 0, pciDomainID : 0, tccDriver : 0, asyncEngineCount : 2, unifiedAddressing : 1, memoryClockRate : 7001000, memoryBusWidth : 256, l2CacheSize : 4194304, persistingL2CacheMaxSize : 3145728, maxThreadsPerMultiProcessor : 1536, streamPrioritiesSupported : 1, globalL1CacheSupported : 1, localL1CacheSupported : 1, sharedMemPerMultiprocessor : 102400, regsPerMultiprocessor : 65536, managedMemory : 1, isMultiGpuBoard : 0, multiGpuBoardGroupID : 0, hostNativeAtomicSupported : 0, singleToDoublePrecisionPerfRatio : 32, pageableMemoryAccess : 0, concurrentManagedAccess : 1, computePreemptionSupported : 1, canUseHostPointerForRegisteredMem : 1, cooperativeLaunch : 1, cooperativeMultiDeviceLaunch : 1, sharedMemPerBlockOptin : 101376, pageableMemoryAccessUsesHostPageTables : 0, directManagedMemAccessFromHost : 0, maxBlocksPerMultiProcessor : 16, accessPolicyMaxWindowSize : 134213632, reservedSharedMemPerBlock : 1024, hostRegisterSupported : 0, sparseCudaArraySupported : 0, hostRegisterReadOnlySupported : 0, timelineSemaphoreInteropSupported : 0, memoryPoolsSupported : 0, gpuDirectRDMASupported : 0, gpuDirectRDMAFlushWritesOptions : 0, gpuDirectRDMAWritesOrdering : 0, memoryPoolSupportedHandleTypes : 0, deferredMappingCudaArraySupported : 0, ipcEventSupported : 0, clusterLaunch : 0, unifiedFunctionPointers : 0, reserved2 : [0, 0], reserved1 : [0], reserved : [0, 0, 0, 0, 0, 0, 0, 0, 0, 0, 0, 0, 0, 0, 0, 0, 0, 0, 0, 0, 0, 0, 0, 0, 0, 0, 0, 0, 0, 0, 0, 0, 0, 0, 0, 0, 0, 0, 0, 0, 0, 0, 0, 0, 0, 0, 0, 0, 0, 0, 0, 0, 0, 0, 0, 0, 0, 0, 0, 0]", "best_config": {"nvml_gr_clock": 840, "nvml_mem_clock": 6501, "GEMMK": 0, "MWG": 128, "NWG": 128, "KWG": 32, "MDIMC": 16, "NDIMC": 8, "MDIMA": 32, "NDIMB": 32, "KWI": 2, "VWM": 4, "VWN": 2, "STRM": 1, "STRN": 0, "SA": 1, "SB": 1, "KREG": 1, "PRECISION": 32, "REPEAT": 48, "core_freqs": [840.0, 840.0, 840.0, 840.0, 840.0, 840.0, 840.0, 840.0, 840.0, 840.0, 840.0, 840.0, 840.0, 840.0, 840.0, 840.0, 840.0, 840.0, 840.0, 840.0, 840.0, 840.0, 840.0, 840.0, 840.0, 840.0, 840.0, 840.0, 840.0, 840.0, 840.0, 840.0], "core_freq": 840.0, "mem_freqs": [6501.0, 6501.0, 6501.0, 6501.0, 6501.0, 6501.0, 6501.0, 6501.0, 6501.0, 6501.0, 6501.0, 6501.0, 6501.0, 6501.0, 6501.0, 6501.0, 6501.0, 6501.0, 6501.0, 6501.0, 6501.0, 6501.0, 6501.0, 6501.0, 6501.0, 6501.0, 6501.0, 6501.0, 6501.0, 6501.0, 6501.0, 6501.0], "mem_freq": 6501.0, "temperatures": [55.0, 55.0, 55.952586206896555, 56.0, 56.0, 56.0, 56.336032388663966, 57.0, 57.0, 57.0, 57.0, 57.0, 57.0, 57.0, 57.0, 57.0, 57.0, 57.0, 57.0, 57.0, 57.197916666666664, 58.0, 58.0, 58.0, 58.0, 58.0, 58.0, 58.0, 58.0, 58.0, 58.0, 58.0], "temperature": 57.0777042269446, "num_regs": 168, "time": 18.91155183315277, "times": [18.990079879760742, 18.933759689331055, 18.912256240844727, 18.908159255981445, 18.939903259277344, 18.916351318359375, 18.899967193603516, 18.923519134521484, 18.929664611816406, 18.909183502197266, 18.928640365600586, 18.923519134521484, 18.887680053710938, 18.889728546142578, 18.899967193603516, 18.910207748413086, 18.910207748413086, 18.892799377441406, 18.88153648376465, 18.905088424682617, 18.908159255981445, 18.928640365600586, 18.924543380737305, 18.909183502197266, 18.918399810791016, 18.936832427978516, 18.879487991333008, 18.88153648376465, 18.878463745117188, 18.893823623657227, 18.914304733276367, 18.904064178466797], "compile_time": 483.40512393042445, "verification_time": 0, "benchmark_time": 613.8057918287814, "GFLOP/s": 7269.234651754211, "strategy_time": 0, "framework_time": 1.625127624720335, "timestamp": "2024-03-27 14:48:49.881095+00:00"}, "total_framework_time": 1026.807260233909, "total_strategy_time": 0, "total_compile_time": 47865.839338861406, "total_verification_time": 0, "total_benchmark_time": 61595.45734617859, "overhead_time": 1131.2839747406542, "execution_time": 111.62000465393066}